{
  "align": {
    "type": "string"
  },
  "backgroundImages": {
    "type": "array",
    "default": [],
    "items": {
      "type": "object"
    }
  },
  "filterColor": {
    "type": "string",
    "default": "rgba(0, 0, 0, 0)"
  },
  "h2Text": {
    "type": "string",
    "default": ""
  },
  "h2TextAlignment": {
    "type": "string",
    "default": "center"
  },
  "h2FontSize": {
    "type": "string",
    "default": "50px"
  },
  "h2MarginBottom": {
    "type": "string",
    "default": "20px"
  },
  "h2Color": {
    "type": "string",
    "default": "#fff"
  },
  "buttonText": {
    "type": "string",
    "default": "Button"
  },
  "height": {
    "type": "string",
    "default": "550px"
  },
  "elementsPosition": {
    "type": "object",
    "default": {
      "left": {
        "value": 50,
        "units": "%"
      },
      "top": {
        "value": 50,
        "units": "%"
      }
    }
  },
  "elementsPositionLimits": {
    "type": "object",
    "default": {
      "x": {
        "lower": 0,
        "upper": 100
      },
      "y": {
        "lower": 0,
        "upper": 100
      }
    }
  },
  "elementsTranslate": {
    "type": "object",
    "default": {
      "left": {
        "value": -50,
        "units": "%"
      },
      "top": {
        "value": -50,
        "units": "%"
      }
    }
  },
  "innerBlocks": {
    "type": "object",
    "default": {}
  }
}
